pysigview_cs/__init__.py
pysigview_cs/source_manager.py
pysigview_cs/cs/__init__.py
pysigview_cs/cs/client.py
pysigview_cs/cs/directory_tree.py
pysigview_cs/cs/server.py
pysigview_cs/file_formats/__init__.py
pysigview_cs/file_formats/d.py
pysigview_cs/file_formats/formats.py
pysigview_cs/file_formats/mefd.py
pysigview_cs-0.1.3.dist-info/DESCRIPTION.rst
pysigview_cs-0.1.3.dist-info/METADATA
pysigview_cs-0.1.3.dist-info/RECORD
pysigview_cs-0.1.3.dist-info/WHEEL
pysigview_cs-0.1.3.dist-info/metadata.json
pysigview_cs-0.1.3.dist-info/top_level.txt
