Metadata-Version: 2.0
Name: pysigview-cs
Version: 0.1.3
Summary: Pysigview client-server
Home-page: https://github.com/ICRC-BME/PySigView_cs
Author: Jan Cimbalnik
Author-email: jan.cimbalnik@fnusa.cz
License: Apache 2.0
Keywords: client server pysigview signals
Platform: Linux
Platform: MacOS
Classifier: License :: OSI Approved :: MIT License
Classifier: Operating System :: MacOS
Classifier: Operating System :: POSIX :: Linux
Classifier: Programming Language :: Python :: 3
Classifier: Development Status :: 5 - Production/Stable
Classifier: Topic :: Scientific/Engineering
Requires-Dist: numpy
Requires-Dist: pyzmq
Requires-Dist: pymef (>=0.2)
Requires-Dist: pydread
